[
	{
		"speaker": "Narrator", 
		"line": "Good. What did he say?"
	},
	{
		"speaker": "Narrator", 
		"line": "He told me to get over myself and just do it."
	},
	{
		"speaker": "Narrator", 
		"line": "I thought about what you said and about what he said."
	},
	{
		"speaker": "Narrator", 
		"line": "And his way, I get to have sex tonight, so"
	},
	{
		"speaker": "Narrator", 
		"line": "What is this in my pocket?"
	},
	{
		"speaker": "Narrator", 
		"line": "Why, it's Joey's porno movie!"
	},
	{
		"speaker": "Narrator", 
		"line": "Pop it in!"
	},
	{
		"speaker": "Narrator", 
		"line": "I'm fine, if you're okay watching a video"
	},
	{
		"speaker": "Narrator", 
		"line": "filled with two-nippled people."
	},
	{
		"speaker": "Narrator", 
		"line": "People having sex. That's just what I need to see."
	},
	{
		"speaker": "Narrator", 
		"line": "What's wrong with people having sex?"
	},
	{
		"speaker": "Narrator", 
		"line": "Well, you know, these movies are offensive"
	},
	{
		"speaker": "Narrator", 
		"line": "and degrading to women and females"
	},
	{
		"speaker": "Narrator", 
		"line": "And the lighting's always unflattering."
	},
	{
		"speaker": "Narrator", 
		"line": "- Monica, help me out here. - Hell, I wanna see Joey!"
	},
	{
		"speaker": "Narrator", 
		"line": "So is there a story? Or do they just start doing it right"
	},
	{
		"speaker": "Narrator", 
		"line": "Oh. Never mind."
	},
	{
		"speaker": "Narrator", 
		"line": "Wait a minute. That is the craziest typing test I've ever seen."
	},
	{
		"speaker": "Narrator", 
		"line": "All I say is, she'd better get the job."
	},
	{
		"speaker": "Narrator", 
		"line": "Looks to me like he's the one getting the job."
	},
	{
		"speaker": "Narrator", 
		"line": "Here I come."
	},
	{
		"speaker": "Narrator", 
		"line": "See, I'm coming to fix the copier."
	},
	{
		"speaker": "Narrator", 
		"line": "I can't get to the copier. I'm thinking, What do I do?"
	},
	{
		"speaker": "Narrator", 
		"line": "So I just watch them have sex."
	},
	{
		"speaker": "Narrator", 
		"line": "Then I say Here's my line!"
	},
	{
		"speaker": "Narrator", 
		"line": "You know, that's bad for the paper tray."
	},
	{
		"speaker": "Narrator", 
		"line": "Nice work, my friend!"
	},
	{
		"speaker": "Narrator", 
		"line": "Wait, you see me again. Hang on, the guy's butt's blocking me."
	},
	{
		"speaker": "Narrator", 
		"line": "There I am. There I am. There I am"
	},
	{
		"speaker": "Narrator", 
		"line": "So what's up? You came to see me yesterday."
	},
	{
		"speaker": "Narrator", 
		"line": "I kind of need a divorce."
	},
	{
		"speaker": "Narrator", 
		"line": "O"
	},
	{
		"speaker": "Narrator", 
		"line": "kay."
	},
	{
		"speaker": "Narrator", 
		"line": "How come?"
	},
	{
		"speaker": "Narrator", 
		"line": "Actually, I'm getting married again."
	},
	{
		"speaker": "Narrator", 
		"line": "What?"
	},
	{
		"speaker": "Narrator", 
		"line": "I don't know how to tell you this."
	},
	{
		"speaker": "Narrator", 
		"line": "I'm straight."
	},
	{
		"speaker": "Narrator", 
		"line": "I don't understand. How can you be straight?"
	},
	{
		"speaker": "Narrator", 
		"line": "You're so smart and funny"
	},
	{
		"speaker": "Narrator", 
		"line": "and you throw such great Academy Award parties!"
	},
	{
		"speaker": "Narrator", 
		"line": "That's what I kept telling myself."
	},
	{
		"speaker": "Narrator", 
		"line": "But you reach a point where you can't live a lie anymore."
	},
	{
		"speaker": "Narrator", 
		"line": "How long have you known?"
	},
	{
		"speaker": "Narrator", 
		"line": "I guess on some level I always knew I was straight."
	},
	{
		"speaker": "Narrator", 
		"line": "I thought I was supposed to be something else."
	},
	{
		"speaker": "Narrator", 
		"line": "I'm an ice dancer, all my friends are gay. I was just trying to fit in."
	},
	{
		"speaker": "Narrator", 
		"line": "And there's actually a woman?"
	},
	{
		"speaker": "Narrator", 
		"line": "Her name's Debra."
	},
	{
		"speaker": "Narrator", 
		"line": "Well, is she the first that you've been with?"
	},
	{
		"speaker": "Narrator", 
		"line": "I've never told you this"
	},
	{
		"speaker": "Narrator", 
		"line": "but there were one or two times back in college when"
	},
	{
		"speaker": "Narrator", 
		"line": "I'd get drunk, go to a straight bar"
	},
	{
		"speaker": "Narrator", 
		"line": "and wake up with a woman next to me."
	},
	{
		"speaker": "Narrator", 
		"line": "I told myself it was the liquor, and everyone experiments in college."
	},
	{
		"speaker": "Narrator", 
		"line": "Sure."
	},
	{
		"speaker": "Narrator", 
		"line": "Now I know I don't have a choice. I was born this way!"
	},
	{
		"speaker": "Narrator", 
		"line": "I don't know what to say."
	},
	{
		"speaker": "Narrator", 
		"line": "You're married to someone for six years and you think you know him."
	},
	{
		"speaker": "Narrator", 
		"line": "And then one day he says, Oh, I'm not gay!"
	},
	{
		"speaker": "Narrator", 
		"line": "I'm still me."
	},
	{
		"speaker": "Narrator", 
		"line": "Why couldn't you just have figured this out six years ago?"
	},
	{
		"speaker": "Narrator", 
		"line": "You know, it still smells like monkey in there."
	},
	{
		"speaker": "Narrator", 
		"line": "That saves us the conversation."
	},
	{
		"speaker": "Narrator", 
		"line": "This has been great, but I'm officially wiped."
	},
	{
		"speaker": "Narrator", 
		"line": "Me too. We should get going."
	},
	{
		"speaker": "Narrator", 
		"line": "No! Come on, you guys!"
	},
	{
		"speaker": "Narrator", 
		"line": "Come on, it's only 11:30."
	},
	{
		"speaker": "Narrator", 
		"line": "Let's just talk. We never just hang out and talk anymore."
	},
	{
		"speaker": "Narrator", 
		"line": "Rachel, that's all we do."
	},
	{
		"speaker": "Narrator", 
		"line": "Maybe that's all we do. What about Julie?"
	},
	{
		"speaker": "Narrator", 
		"line": "What about Julie?"
	},
	{
		"speaker": "Narrator", 
		"line": "You have been in our lives for nearly two months now"
	},
	{
		"speaker": "Narrator", 
		"line": "and we don't really know you."
	},
	{
		"speaker": "Narrator", 
		"line": "I mean, who is Julie?"
	},
	{
		"speaker": "Narrator", 
		"line": "What do you like? What don't you like?"
	},
	{
		"speaker": "Narrator", 
		"line": "We want to know everything."
	},
	{
		"speaker": "Narrator", 
		"line": "Well, that could take awhile."
	},
	{
		"speaker": "Narrator", 
		"line": "So?"
	},
	{
		"speaker": "Narrator", 
		"line": "Who here does not have the time to get to know Julie?"
	},
	{
		"speaker": "Narrator", 
		"line": "I got the time to get to know Julie."
	},
	{
		"speaker": "Narrator", 
		"line": "I know her pretty well. Can I go?"
	},
	{
		"speaker": "Narrator", 
		"line": "That's fine."
	},
	{
		"speaker": "Narrator", 
		"line": "Let's start with your childhood. What was that like?"
	},
	{
		"speaker": "Narrator", 
		"line": "In a nutshell"
	},
	{
		"speaker": "Narrator", 
		"line": "So, have you told your parents?"
	},
	{
		"speaker": "Narrator", 
		"line": "No, but it'll be okay. They're pretty cool."
	},
	{
		"speaker": "Narrator", 
		"line": "My brother's straight, so"
	},
	{
		"speaker": "Narrator", 
		"line": "Here you go."
	},
	{
		"speaker": "Narrator", 
		"line": "You know what? I just have one more question."
	},
	{
		"speaker": "Narrator", 
		"line": "If you had figured this out sooner, and I had been around"
	},
	{
		"speaker": "Narrator", 
		"line": "do you think I would have been the one?"
	},
	{
		"speaker": "Narrator", 
		"line": "No. Don't tell me."
	},
	{
		"speaker": "Narrator", 
		"line": "I don't think either answer would make me feel better. Here."
	},
	{
		"speaker": "Narrator", 
		"line": "I love you, Phoebe."
	},
	{
		"speaker": "Narrator", 
		"line": "So your brother's straight, huh?"
	},
	{
		"speaker": "Narrator", 
		"line": "Seriously."
	},
	{
		"speaker": "Narrator", 
		"line": "- And my second-grade teacher was Miss Thomas"
	},
	{
		"speaker": "Narrator", 
		"line": "and my first-grade teacher was Mrs. Cobb."
	},
	{
		"speaker": "Narrator", 
		"line": "Mrs. Gobb?"
	},
	{
		"speaker": "Narrator", 
		"line": "No, Cobb. Like cobb salad."
	},
	{
		"speaker": "Narrator", 
		"line": "What exactly is in a cobb salad?"
	},
	{
		"speaker": "Narrator", 
		"line": "I'm going home."
	},
	{
		"speaker": "Narrator", 
		"line": "Boy, that Julie's a talker, huh?"
	},
	{
		"speaker": "Narrator", 
		"line": "Good night."
	},
	{
		"speaker": "Narrator", 
		"line": "It's pretty late. You're probably not still planning on"
	},
	{
		"speaker": "Narrator", 
		"line": "No, I am."
	},
	{
		"speaker": "Narrator", 
		"line": "Are you nervous?"
	},
	{
		"speaker": "Narrator", 
		"line": "I have done it before."
	},
	{
		"speaker": "Narrator", 
		"line": "I mean, how are you gonna handle it?"
	},
	{
		"speaker": "Narrator", 
		"line": "Are you gonna talk about it beforehand? Are you just gonna pounce?"
	},
	{
		"speaker": "Narrator", 
		"line": "I don't know. I guess I'm just gonna"
	},
	{
		"speaker": "Narrator", 
		"line": "see what happens."
	},
	{
		"speaker": "Narrator", 
		"line": "Good luck!"
	},
	{
		"speaker": "Narrator", 
		"line": "What?"
	},
	{
		"speaker": "Narrator", 
		"line": "Nothing"
	},
	{
		"speaker": "Narrator", 
		"line": "It is your first time with her, and if the first time doesn't go well"
	},
	{
		"speaker": "Narrator", 
		"line": "well then, that's pretty darn hard to recover from."
	},
	{
		"speaker": "Narrator", 
		"line": "Okay, now I'm nervous."
	},
	{
		"speaker": "Narrator", 
		"line": "Maybe you should put it off."
	},
	{
		"speaker": "Narrator", 
		"line": "No, I don't want to put it off!"
	},
	{
		"speaker": "Narrator", 
		"line": "I spent last year being so unbelievably miserable."
	},
	{
		"speaker": "Narrator", 
		"line": "And now I'm actually happy."
	},
	{
		"speaker": "Narrator", 
		"line": "You know, I mean really happy."
	},
	{
		"speaker": "Narrator", 
		"line": "I just don't wanna"
	},
	{
		"speaker": "Narrator", 
		"line": "I don't wanna mess it up, you know?"
	},
	{
		"speaker": "Narrator", 
		"line": "I know."
	},
	{
		"speaker": "Narrator", 
		"line": "I'm sorry."
	},
	{
		"speaker": "Narrator", 
		"line": "It's not your fault."
	},
	{
		"speaker": "Narrator", 
		"line": "Right."
	},
	{
		"speaker": "Narrator", 
		"line": "Maybe it doesn't have to be this tough."
	},
	{
		"speaker": "Narrator", 
		"line": "Maybe you were on the right track with that whole spontaneous thing."
	},
	{
		"speaker": "Narrator", 
		"line": "- Women really like that. - Really?"
	},
	{
		"speaker": "Narrator", 
		"line": "I mean if it were me, I'd want you to"
	},
	{
		"speaker": "Narrator", 
		"line": "I don't know, catch me off guard with a really"
	},
	{
		"speaker": "Narrator", 
		"line": "good kiss."
	},
	{
		"speaker": "Narrator", 
		"line": "Really sort of soft at first."
	},
	{
		"speaker": "Narrator", 
		"line": "And then maybe brush the hair away from my face."
	},
	{
		"speaker": "Narrator", 
		"line": "And then look far into my eyes"
	},
	{
		"speaker": "Narrator", 
		"line": "in a way that lets me know something"
	},
	{
		"speaker": "Narrator", 
		"line": "amazing is about to happen."
	},
	{
		"speaker": "Narrator", 
		"line": "And then, I don't know, then"
	},
	{
		"speaker": "Narrator", 
		"line": "you'd pull me really close to you so that"
	},
	{
		"speaker": "Narrator", 
		"line": "so that I'd be pressed up right against you."
	},
	{
		"speaker": "Narrator", 
		"line": "And it would get kind of"
	},
	{
		"speaker": "Narrator", 
		"line": "sweaty"
	},
	{
		"speaker": "Narrator", 
		"line": "and blurry."
	},
	{
		"speaker": "Narrator", 
		"line": "And then it's just happening."
	},
	{
		"speaker": "Narrator", 
		"line": "Thanks, Rach. Good night!"
	},
	{
		"speaker": "Narrator", 
		"line": "Oh, God!"
	},
	{
		"speaker": "Narrator", 
		"line": "Good morning!"
	},
	{
		"speaker": "Narrator", 
		"line": "Well, somebody got some last night!"
	}
]