[
	{
		"speaker": "Narrator", 
		"line": "How did this happen  "
	},
	{
		"speaker": "Narrator", 
		"line": "I kind of ran into him last night  "
	},
	{
		"speaker": "Narrator", 
		"line": " Where  At his apartment "
	},
	{
		"speaker": "Narrator", 
		"line": "Is this juice  "
	},
	{
		"speaker": "Narrator", 
		"line": "And the fact that you dumped him because he hit on Phoebe "
	},
	{
		"speaker": "Narrator", 
		"line": "Oh God I know I'm pathetic I'm a loser "
	},
	{
		"speaker": "Narrator", 
		"line": "Honey you're not pathetic You're just sad "
	},
	{
		"speaker": "Narrator", 
		"line": "People do stupid things when they're upset "
	},
	{
		"speaker": "Narrator", 
		"line": "My God if I had a nickel for every guy I wish I hadn't "
	},
	{
		"speaker": "Narrator", 
		"line": "But this is about your horrible mistake "
	},
	{
		"speaker": "Narrator", 
		"line": "Sorry we're late  "
	},
	{
		"speaker": "Narrator", 
		"line": "We were  "
	},
	{
		"speaker": "Narrator", 
		"line": "Well there was touching  "
	},
	{
		"speaker": "Narrator", 
		"line": "Hey Ross  "
	},
	{
		"speaker": "Narrator", 
		"line": "What a  "
	},
	{
		"speaker": "Narrator", 
		"line": "What are you doing here  "
	},
	{
		"speaker": "Narrator", 
		"line": "I do Raquel  "
	},
	{
		"speaker": "Narrator", 
		"line": "So he's back  "
	},
	{
		"speaker": "Narrator", 
		"line": "Yeah he's back Is that a problem "
	},
	{
		"speaker": "Narrator", 
		"line": "No not a problem  "
	},
	{
		"speaker": "Narrator", 
		"line": "Good Glad it's not a problem  "
	},
	{
		"speaker": "Narrator", 
		"line": "You're gonna have to not touch my ass  "
	},
	{
		"speaker": "Narrator", 
		"line": "Despite the yummy bagels and palpable tension "
	},
	{
		"speaker": "Narrator", 
		"line": "my pants need to be altered  "
	},
	{
		"speaker": "Narrator", 
		"line": "When you see Frankie tell him Joey Tribbiani says hello "
	},
	{
		"speaker": "Narrator", 
		"line": "He'll know what it means  "
	},
	{
		"speaker": "Narrator", 
		"line": "You sure he'll crack that code  "
	},
	{
		"speaker": "Narrator", 
		"line": "It's funny The last time Paolo was here my hair was so much cuter "
	},
	{
		"speaker": "Narrator", 
		"line": "All right  "
	},
	{
		"speaker": "Narrator", 
		"line": "But you have to promise that you will not be all controlly and bossy "
	},
	{
		"speaker": "Narrator", 
		"line": "and all Monica about it  "
	},
	{
		"speaker": "Narrator", 
		"line": "I promise  "
	},
	{
		"speaker": "Narrator", 
		"line": "All right let's see  "
	},
	{
		"speaker": "Narrator", 
		"line": "Now some of you are gonna get cut and some of you aren't "
	},
	{
		"speaker": "Narrator", 
		"line": "But I promise none of you will feel a thing "
	},
	{
		"speaker": "Narrator", 
		"line": " That's it I quit  What I didn't say anything "
	},
	{
		"speaker": "Narrator", 
		"line": "But this isn't the face of a person who trusts a person "
	},
	{
		"speaker": "Narrator", 
		"line": "This is the face of a person who you know "
	},
	{
		"speaker": "Narrator", 
		"line": "doesn't trust a person  "
	},
	{
		"speaker": "Narrator", 
		"line": "I'm sorry I'm sorry  "
	},
	{
		"speaker": "Narrator", 
		"line": "It's just a little shorter than what we had discussed "
	},
	{
		"speaker": "Narrator", 
		"line": "Would you relax I know what I am doing "
	},
	{
		"speaker": "Narrator", 
		"line": "This is how he wears it  "
	},
	{
		"speaker": "Narrator", 
		"line": "How who wears it  "
	},
	{
		"speaker": "Narrator", 
		"line": "Demi Moore  "
	},
	{
		"speaker": "Narrator", 
		"line": "Demi Moore is not a he  "
	},
	{
		"speaker": "Narrator", 
		"line": "Well he was a he in Arthur and in 10 "
	},
	{
		"speaker": "Narrator", 
		"line": "That's Dudley Moore  "
	},
	{
		"speaker": "Narrator", 
		"line": "I said I wanted it like Demi Moore  "
	},
	{
		"speaker": "Narrator", 
		"line": "Oh my God  "
	},
	{
		"speaker": "Narrator", 
		"line": "Oh God  "
	},
	{
		"speaker": "Narrator", 
		"line": "Oh my God I'm sorry  "
	},
	{
		"speaker": "Narrator", 
		"line": "Which one is Demi Moore  "
	},
	{
		"speaker": "Narrator", 
		"line": "She's the actress that was in Disclosure Indecent Proposal Ghost "
	},
	{
		"speaker": "Narrator", 
		"line": "She's got gorgeous hair  "
	},
	{
		"speaker": "Narrator", 
		"line": "I know  "
	},
	{
		"speaker": "Narrator", 
		"line": "How long do you want the cuffs  "
	},
	{
		"speaker": "Narrator", 
		"line": "At least as long as I have the pants  "
	},
	{
		"speaker": "Narrator", 
		"line": "I just got that  "
	},
	{
		"speaker": "Narrator", 
		"line": "Now we'll do your inseam  "
	},
	{
		"speaker": "Narrator", 
		"line": "How is she  "
	},
	{
		"speaker": "Narrator", 
		"line": "It's too soon to tell  "
	},
	{
		"speaker": "Narrator", 
		"line": "She's resting which is a good sign  "
	},
	{
		"speaker": "Narrator", 
		"line": "How's the hair  "
	},
	{
		"speaker": "Narrator", 
		"line": "I'm not gonna lie to you It doesn't look good "
	},
	{
		"speaker": "Narrator", 
		"line": "I put a clip on one side which seems to have stopped the curling "
	},
	{
		"speaker": "Narrator", 
		"line": "Can we see her  "
	},
	{
		"speaker": "Narrator", 
		"line": "Your hair looks too good It'd upset her "
	},
	{
		"speaker": "Narrator", 
		"line": "Ross you come on in  "
	},
	{
		"speaker": "Narrator", 
		"line": "Well how you doing  "
	},
	{
		"speaker": "Narrator", 
		"line": "I'm okay  "
	},
	{
		"speaker": "Narrator", 
		"line": "That bad huh  "
	},
	{
		"speaker": "Narrator", 
		"line": "Look I can sense when women are depressed and vulnerable "
	},
	{
		"speaker": "Narrator", 
		"line": "It's one of my gifts  "
	},
	{
		"speaker": "Narrator", 
		"line": "Joey when I saw him get off that plane with her "
	},
	{
		"speaker": "Narrator", 
		"line": "I really thought I just hit rock bottom "
	},
	{
		"speaker": "Narrator", 
		"line": "But today it's like there's rock bottom "
	},
	{
		"speaker": "Narrator", 
		"line": "50 feet of crap  "
	},
	{
		"speaker": "Narrator", 
		"line": "then me  "
	},
	{
		"speaker": "Narrator", 
		"line": "Tell Ross how you feel  "
	},
	{
		"speaker": "Narrator", 
		"line": "Come on how can I just tell him What about Julie "
	},
	{
		"speaker": "Narrator", 
		"line": "What about her They've only been going out for two weeks "
	},
	{
		"speaker": "Narrator", 
		"line": "Ross has been in love with you for 10 years "
	},
	{
		"speaker": "Narrator", 
		"line": "I don't know I don't know  "
	},
	{
		"speaker": "Narrator", 
		"line": "I've been with my share of women  "
	},
	{
		"speaker": "Narrator", 
		"line": "I've been with a lot of people's share of women "
	},
	{
		"speaker": "Narrator", 
		"line": "But the point is  "
	},
	{
		"speaker": "Narrator", 
		"line": "I've never felt about anyone the way Ross felt about you "
	},
	{
		"speaker": "Narrator", 
		"line": "Really  "
	},
	{
		"speaker": "Narrator", 
		"line": "Yo paisan  "
	},
	{
		"speaker": "Narrator", 
		"line": "Can I talk to you for a sec  "
	},
	{
		"speaker": "Narrator", 
		"line": "Your tailor  "
	},
	{
		"speaker": "Narrator", 
		"line": "is a very bad man  "
	},
	{
		"speaker": "Narrator", 
		"line": "What are you talking about  "
	},
	{
		"speaker": "Narrator", 
		"line": "Hey what's going on  "
	},
	{
		"speaker": "Narrator", 
		"line": "Joey's tailor  "
	},
	{
		"speaker": "Narrator", 
		"line": "took advantage of me  "
	},
	{
		"speaker": "Narrator", 
		"line": "No way I've been going to the guy for 12 years "
	},
	{
		"speaker": "Narrator", 
		"line": "He said he was gonna do my inseam  "
	},
	{
		"speaker": "Narrator", 
		"line": "Then he ran his hand up my leg and then there was definite "
	},
	{
		"speaker": "Narrator", 
		"line": "What  "
	},
	{
		"speaker": "Narrator", 
		"line": "Cupping  "
	},
	{
		"speaker": "Narrator", 
		"line": "That's how they do pants  "
	},
	{
		"speaker": "Narrator", 
		"line": "First they go up one side they move it over "
	},
	{
		"speaker": "Narrator", 
		"line": "Then they go up the other side move it back then they do the rear "
	},
	{
		"speaker": "Narrator", 
		"line": "Ross tell him Isn't that how a tailor measures pants "
	},
	{
		"speaker": "Narrator", 
		"line": "Yes yes it is In prison "
	},
	{
		"speaker": "Narrator", 
		"line": "What's the matter with you  "
	},
	{
		"speaker": "Narrator", 
		"line": "What  "
	},
	{
		"speaker": "Narrator", 
		"line": "That's not  "
	},
	{
		"speaker": "Narrator", 
		"line": "Oh my God  "
	},
	{
		"speaker": "Narrator", 
		"line": "Even Mary Tyler Moore would've been better "
	},
	{
		"speaker": "Narrator", 
		"line": "I like it  "
	},
	{
		"speaker": "Narrator", 
		"line": "I do I think it's a 10  "
	},
	{
		"speaker": "Narrator", 
		"line": "Thank you  "
	},
	{
		"speaker": "Narrator", 
		"line": "My hair is very amused  "
	},
	{
		"speaker": "Narrator", 
		"line": "Come on things could be worse  "
	},
	{
		"speaker": "Narrator", 
		"line": "You could get caught between the moon and New York City "
	},
	{
		"speaker": "Narrator", 
		"line": "I know it's crazy but it's true  "
	},
	{
		"speaker": "Narrator", 
		"line": "Thank you  "
	},
	{
		"speaker": "Narrator", 
		"line": "Well I gotta go Bye  "
	},
	{
		"speaker": "Narrator", 
		"line": "Bye Rach  "
	},
	{
		"speaker": "Narrator", 
		"line": "Wait are you leaving  "
	},
	{
		"speaker": "Narrator", 
		"line": "That's what I meant by bye  "
	},
	{
		"speaker": "Narrator", 
		"line": "Can I talk to you for a sec  "
	},
	{
		"speaker": "Narrator", 
		"line": "When the doctor does that hernia test "
	},
	{
		"speaker": "Narrator", 
		"line": "That's okay  "
	},
	{
		"speaker": "Narrator", 
		"line": "What's going on  "
	},
	{
		"speaker": "Narrator", 
		"line": "Well okay first of all  "
	},
	{
		"speaker": "Narrator", 
		"line": "Paolo and I are not back together  "
	},
	{
		"speaker": "Narrator", 
		"line": "That was a stupid thing I did  "
	},
	{
		"speaker": "Narrator", 
		"line": "If I could go back in time and do it again "
	},
	{
		"speaker": "Narrator", 
		"line": "well I wouldn't  "
	},
	{
		"speaker": "Narrator", 
		"line": "Second of all  "
	},
	{
		"speaker": "Narrator", 
		"line": "What  "
	},
	{
		"speaker": "Narrator", 
		"line": "Is this one of those things where you break up with a guy "
	},
	{
		"speaker": "Narrator", 
		"line": "I tell you what I think  "
	},
	{
		"speaker": "Narrator", 
		"line": "and the next day you get back together with him "
	},
	{
		"speaker": "Narrator", 
		"line": "and I look like a complete idiot "
	},
	{
		"speaker": "Narrator", 
		"line": "Well then I think the guy's scum  "
	},
	{
		"speaker": "Narrator", 
		"line": "I hate him I mean I actually I physically hate him "
	},
	{
		"speaker": "Narrator", 
		"line": "I always have  "
	},
	{
		"speaker": "Narrator", 
		"line": "And you are way too good to be with a guy like that "
	},
	{
		"speaker": "Narrator", 
		"line": "Really  "
	},
	{
		"speaker": "Narrator", 
		"line": "You deserve to be with someone who appreciates you "
	},
	{
		"speaker": "Narrator", 
		"line": "and who gets how funny  "
	},
	{
		"speaker": "Narrator", 
		"line": "and sweet and amazing  "
	},
	{
		"speaker": "Narrator", 
		"line": "and adorable and sexy you are  "
	},
	{
		"speaker": "Narrator", 
		"line": "You know Someone who wakes up every morning thinking "
	},
	{
		"speaker": "Narrator", 
		"line": "Oh my God I'm with Rachel  "
	},
	{
		"speaker": "Narrator", 
		"line": "You know Someone who makes you feel good "
	},
	{
		"speaker": "Narrator", 
		"line": "Like the way I do with Julie  "
	},
	{
		"speaker": "Narrator", 
		"line": "Was there a second of all  "
	},
	{
		"speaker": "Narrator", 
		"line": "No I think that was the whole all  "
	},
	{
		"speaker": "Narrator", 
		"line": "I gotta go  "
	},
	{
		"speaker": "Narrator", 
		"line": "Thanks  "
	},
	{
		"speaker": "Narrator", 
		"line": "No I swear to God Dad  "
	},
	{
		"speaker": "Narrator", 
		"line": "That's not how they measure pants  "
	},
	{
		"speaker": "Narrator", 
		"line": "I was thinking of doing it shorter like Andie MacDowell's haircut "
	},
	{
		"speaker": "Narrator", 
		"line": " Yeah I could do that  Really "
	},
	{
		"speaker": "Narrator", 
		"line": " You wanna do it now  Great "
	},
	{
		"speaker": "Narrator", 
		"line": "See you  "
	},
	{
		"speaker": "Narrator", 
		"line": "I just wanna make really sure this time "
	},
	{
		"speaker": "Narrator", 
		"line": "Andie MacDowell is the girl from Four Weddings and a Funeral right "
	},
	{
		"speaker": "Narrator", 
		"line": "No  "
	},
	{
		"speaker": "Narrator", 
		"line": "That's Roddy McDowall  "
	},
	{
		"speaker": "Narrator", 
		"line": "Andie MacDowell is the guy from Planet of the Apes "
	},
	{
		"speaker": "Narrator", 
		"line": " Thank you  You're welcome "
	}
]